pureml_llm/TODO
pureml_llm/accuracy/ai_disclaimer_similarity.py
pureml_llm/accuracy/ban_topics.py
pureml_llm/accuracy/bert_score_f1.py
pureml_llm/accuracy/bert_score_precision.py
pureml_llm/accuracy/bert_score_recall.py
pureml_llm/accuracy/character.py
pureml_llm/accuracy/charcut_mt.py
pureml_llm/accuracy/chrf.py
pureml_llm/accuracy/f1.py
pureml_llm/accuracy/flesch_kincaid_grade.py
pureml_llm/accuracy/flesch_reading_ease.py
pureml_llm/accuracy/fluency.py
pureml_llm/accuracy/gibberish.py
pureml_llm/accuracy/google_bleu.py
pureml_llm/accuracy/mauve_score.py
pureml_llm/accuracy/meteor.py
pureml_llm/accuracy/model.py
pureml_llm/accuracy/nltk_mt.py
pureml_llm/accuracy/progess_bar.py
pureml_llm/accuracy/quasi_exact_match.py
pureml_llm/accuracy/relevance.py
pureml_llm/accuracy/rouge_fmeasure.py
pureml_llm/accuracy/rouge_precision.py
pureml_llm/accuracy/rouge_recall.py
pureml_llm/accuracy/rr_10.py
pureml_llm/accuracy/sentiment.py
pureml_llm/accuracy/stats.py
pureml_llm/accuracy/ter.py
pureml_llm/accuracy/tokenizer_13a.py
pureml_llm/accuracy/transformers_helpers.py
pureml_llm/accuracy/util.py
pureml_llm/accuracy/wer.py
pureml_llm/accuracy_metrics_result.py
pureml_llm/app.py
pureml_llm/assignments.py
pureml_llm/bias/bias.py
pureml_llm/bias/neural_bias.py
pureml_llm/bias/unbias_models.py
pureml_llm/bias_metric_results.py
pureml_llm/frameworks.py
pureml_llm/grade.py
pureml_llm/hallicunation/hallicunation_hugging_face.py
pureml_llm/hallicunation_metrics_result.py
pureml_llm/metric_base.py
pureml_llm/metrics_import.py
pureml_llm/model/base.py
pureml_llm/model/unbias_model.py
pureml_llm/pureml_llm_eval.py
pureml_llm/reports.py
pureml_llm/result.json
pureml_llm/schema.py
pureml_llm/static/index.html
pureml_llm/static/script.js
pureml_llm/static/toxicity.html
pureml_llm/toxicity/identity_attack.py
pureml_llm/toxicity/insult.py
pureml_llm/toxicity/profanity.py
pureml_llm/toxicity/severe_toxicity.py
pureml_llm/toxicity/toxicity_from_prespective.py
pureml_llm-0.1.1.dist-info/METADATA
pureml_llm-0.1.1.dist-info/WHEEL
pureml_llm-0.1.1.dist-info/entry_points.txt
pureml_llm-0.1.1.dist-info/RECORD
